Workbook
Name bonito: '[1]CENTRO DE CUSTO'!#REF!
Name bonito: '[2]CENTRO DE CUSTO'!#REF!
Name bonito: 'CENTRO DE CUSTO'!#REF!
Name bonito_1: #REF!
Name bonito_1: #REF!
Name bonito_10: '[1]CENTRO DE CUSTO'!#REF!
Name bonito_10: '[2]CENTRO DE CUSTO'!#REF!
Name bonito_10: 'CENTRO DE CUSTO'!#REF!
Name bonito_10_1: #REF!
Name bonito_10_1: #REF!
Name bonito_11: '[1]CENTRO DE CUSTO'!#REF!
Name bonito_11: '[2]CENTRO DE CUSTO'!#REF!
Name bonito_11: 'CENTRO DE CUSTO'!#REF!
Name bonito_11_1: #REF!
Name bonito_11_1: #REF!
Name bonito_12: '[1]CENTRO DE CUSTO'!#REF!
Name bonito_12: '[2]CENTRO DE CUSTO'!#REF!
Name bonito_12: 'CENTRO DE CUSTO'!#REF!
Name bonito_12_1: #REF!
Name bonito_12_1: #REF!
Name bonito_13: '[1]CENTRO DE CUSTO'!#REF!
Name bonito_13: '[2]CENTRO DE CUSTO'!#REF!
Name bonito_13: 'CENTRO DE CUSTO'!#REF!
Name bonito_13_1: #REF!
Name bonito_13_1: #REF!
Name bonito_14: '[1]CENTRO DE CUSTO'!#REF!
Name bonito_14: '[2]CENTRO DE CUSTO'!#REF!
Name bonito_14: 'CENTRO DE CUSTO'!#REF!
Name bonito_14_1: #REF!
Name bonito_14_1: #REF!
Name bonito_15: '[1]CENTRO DE CUSTO'!#REF!
Name bonito_15: '[2]CENTRO DE CUSTO'!#REF!
Name bonito_15: 'CENTRO DE CUSTO'!#REF!
Name bonito_15_1: #REF!
Name bonito_15_1: #REF!
Name bonito_16: '[1]CENTRO DE CUSTO'!#REF!
Name bonito_16: '[2]CENTRO DE CUSTO'!#REF!
Name bonito_16: 'CENTRO DE CUSTO'!#REF!
Name bonito_16_1: #REF!
Name bonito_16_1: #REF!
Name bonito_17: '[1]CENTRO DE CUSTO'!#REF!
Name bonito_17: '[2]CENTRO DE CUSTO'!#REF!
Name bonito_17: 'CENTRO DE CUSTO'!#REF!
Name bonito_17_1: #REF!
Name bonito_17_1: #REF!
Name bonito_18: '[1]CENTRO DE CUSTO'!#REF!
Name bonito_18: '[2]CENTRO DE CUSTO'!#REF!
Name bonito_18: 'CENTRO DE CUSTO'!#REF!
Name bonito_18_1: #REF!
Name bonito_18_1: #REF!
Name bonito_19: '[1]CENTRO DE CUSTO'!#REF!
Name bonito_19: '[2]CENTRO DE CUSTO'!#REF!
Name bonito_19: 'CENTRO DE CUSTO'!#REF!
Name bonito_19_1: #REF!
Name bonito_19_1: #REF!
Name bonito_3: '[1]CENTRO DE CUSTO'!#REF!
Name bonito_3: '[2]CENTRO DE CUSTO'!#REF!
Name bonito_3: 'CENTRO DE CUSTO'!#REF!
Name bonito_3_1: #REF!
Name bonito_3_1: #REF!

Sheet Marcopolo PESO ABS
B3: Cálculo para Peso de Peças Plásticas Conforme Composição Química
B6: Espessura | C6: Largura | D6: Comprimento | E6: Tipo | F6: PESO PEÇA
B7: 4 | C7: 15 | D7: 550 | E7: ABS | F7: =IF(E7="ABS",((B7*C7*D7*C63)/1000000),(IF(E7="PEAD",((B7*C7*D7*C64)/1000000),(IF(E7="PP",((B7*C7*D7*C65)/1000000),1)))*1)) -> 0.03498
F8: PESO DA PEÇA +30%
F9: =F7+F7*30% -> 0.045474
Z12: 0.6
Z13: 0.232
Z15: 0.16
Z16: =SUM(Z12:Z15) -> 0.992
B63: ABS | C63: 1.06
B64: PEAD | C64: 0.96
B65: PP | C65: 0.95
B67: ESPESSURA | C67: 4
C68: 5.75
C69: 3
C70: 6.5
C71: 2
C72: 1.5
C73: 5

Sheet ORÇAMENTO INSERTOS
A1: FICHA DE ORÇAMENTO
A2: DESCRIÇÃO DA PEÇA: | F2: CÓDIGO / DESENHO: | J2: LOTE ECONÔMICO: | K2: 100
A3: ESTRUTURA DE PRODUTO
A4: CÓD. MATERIAL | B4: DESCRIÇÃO DOS COMPONENTES | E4: QUANTIDADE | F4: UN | G4: PREÇO ( R$ ) | I4: OBSERVAÇÃO | K4: TOTAL R$
A6: 109299000 | B6: CHAPA DE ACO 1,90 x 1000 x 3000mm - NBR7008 ZEE GRAU 1 Z100 | E6: 0.16 | F6: kg | G6: 7.31 | K6: =E6*G6 -> 1.1696
A7: 1064003000 | B7: CHAPA DE ALUMINIO 1,50 X 1000 X 2000 mm - LIGA 1200 - H14 | F7: kg | G7: 28.75 | K7: =E7*G7 -> 0
A8: 107679000 | B8: CHAPA DE ACO 1,55X1000X2680 - NBR 7008 ZEE - GRAU 2 - Z100 | F8: kg | G8: 6.76 | K8: =E8*G8 -> 0
A9: 107676000 | B9: CHAPA DE ACO 1,20X1500X1795 - ST 05 Z/NBR 7008 ZEE GRAU 2,+Z | F9: kg | G9: 8.54 | K9: =E9*G9 -> 0
A10: 106546000 | B10: CHAPA DE ACO 1,55mm 1200 x 3000mm NBR 7008 ZEE GR1 (Z100) | F10: kg | G10: 4.2525 | K10: =E10*G10 -> 0
A11: 100755000 | B11: =IF(A11="","",VLOOKUP(A11,'[3]Dados MSQUERY Texto 18.02.2014'!$A$1:$D$65533,2,FALSE)) -> CHAPA DE ACO 3,00 mm FQ 1200 x 3000 - SAE 1008 DEC | F11: kg | G11: 6.87 | K11: =E11*G11 -> 0
A12: 100106000 | B12: =IF(A12="","",VLOOKUP(A12,'[3]Dados MSQUERY Texto 18.02.2014'!$A$1:$D$65533,2,FALSE)) -> CHAPA DE ACO 1,50mm FF 1200 x 3000 NBR5915 EM | F12: kg | G12: 5.91 | K12: =E12*G12 -> 0
A13: 109796000 | B13: =IF(A13="","",VLOOKUP(A13,'[3]Dados MSQUERY Texto 18.02.2014'!$A$1:$D$65533,2,FALSE)) -> CHAPA DE ACO 1,90mm FF 1500 x 3000 | F13: kg | G13: 5.0438 | K13: =E13*G13 -> 0
A14: 106039000 | B14: =IF(A14="","",VLOOKUP(A14,'[3]Dados MSQUERY Texto 18.02.2014'!$A$1:$D$65533,2,FALSE)) -> CHAPA DE ACO 4,25mm FQ 1200 x 3000 - NBR 6656 LNE - 38 | F14: kg | G14: 5.849 | K14: =E14*G14 -> 0
A15: 103085000 | B15: =IF(A15="","",VLOOKUP(A15,'[3]Dados MSQUERY Texto 18.02.2014'!$A$1:$D$65533,2,FALSE)) -> CHAPA DE ACO 6,35mm FQ 1200 x 3000 - SAE 1010/20 | F15: kg | G15: 4.22 | K15: =E15*G15 -> 0
A16: 109389000 | B16: CHAPA DE ACO 1,00 x 1500 x 2700mm GI EN10346 DX56D Z140-M-C- | F16: kg | G16: 6.87 | K16: =E16*G16 -> 0
A17: 103209000 | B17: =IF(A17="","",VLOOKUP(A17,'[3]Dados MSQUERY Texto 18.02.2014'!$A$1:$D$65533,2,FALSE)) -> CHAPA DE ACO 1,20mm FF 1200 x 3000 EM | F17: kg | G17: 5.1084 | K17: =E17*G17 -> 0
A18: 106475000 | B18: MANTA DE ISOLAMENTO | F18: M² | G18: 39.283 | K18: =E18*G18 -> 0
A19: 100634000 | B19: =IF(A19="","",VLOOKUP(A19,'[3]Dados MSQUERY Texto 18.02.2014'!$A$1:$D$65533,2,FALSE)) -> PRIMER PRETO IMERSAO BASE D. AGUA | F19: L | G19: 23.53 | K19: =E19*G19 -> 0
A20: 100106000 | B20: CHAPA DE ACO 4,75mm FQD 1200 x 3000 - SAE 1006 DEC | F20: kg | G20: 5.8373 | K20: =E20*G20 -> 0
A21: 107670000 | B21: CHAPA DE AÇO 6,35 x 1200 x 2000mm - NBR 6656 LNE-38 DECOL | F21: kg | G21: 5.91 | K21: =E21*G21 -> 0
A22: SOMATÓRIO DOS VALORES REFERENTES A MATÉRIA-PRIMA................................................ | K22: =SUM(K6:K19) -> 1.1696
A24: OPERAÇÕES EXTERNAS (TERCEIROS)
A25: CÓDIGO | B25: DESCRIÇÃO | C25: QUANTIDADE | D25: UN | E25: FORNECEDOR SERVIÇO | H25: OBSERVAÇÃO | J25: PREÇO UNIT. (R$) | K25: R$
K27: =J27*C27 -> 0
K28: =J28*C28 -> 0
K29: =J29*C29 -> 0
A30: SOMATÓRIO DOS VALORES REFERENTES A OPERAÇÃO EXTERNA (TERCEIROS).............................................. | K30: =SUM(K27:K29) -> 0
A32: PROCESSO DE FABRICAÇÃO | M32: 1
A33: Nº OPERAÇÃO | B33: DESCRIÇÃO DA OPERAÇÃO | C33: CENTRO CUSTO | D33: GRUPO MÁQUINA | E33: DESCRIÇÃO GRUPO MÁQUINA | G33: SET-UP (MINUTOS) | H33: TEMPO OPERAÇÃO (MINUTOS) | I33: Nº DE HOMENS | J33: R$ (SET-UP) | K33: R$ (TEMPO OPERAÇÃO) | M33: 2
L34: =I35*H35 -> 0.3 | M34: 3
A35: 10 | B35: CORTAR CHAPA EM TIRA | C35: 359 | D35: 301-002 | E35: =IF(D35="","",VLOOKUP(D35,'GRUPO MÁQUINA 2025'!A2:B400,2,0)) -> GUILHOTINA MECANICA NEWTON | G35: 4.5 | H35: 0.1 | I35: 3 | J35: =IF(C35<>"",VLOOKUP(C35,'CENTRO DE CUSTO'!$A$3:$C$536,3,0)*G35/$K$2/60,"") -> 0.105 | K35: =IF(C35<>"",VLOOKUP(C35,'CENTRO DE CUSTO'!$A$3:$C$536,3,0)*H35/60*I35,"") -> 0.7 | L35: =I36*H36 -> 0.2 | M35: 4
A36: 20 | B36: CORTAR CHAPA EM BLANK | C36: 359 | D36: 301-002 | E36: =IF(D36="","",VLOOKUP(D36,'GRUPO MÁQUINA 2025'!A3:B401,2,0)) -> GUILHOTINA MECANICA NEWTON | G36: 4.5 | H36: 0.1 | I36: 2 | J36: =IF(C36<>"",VLOOKUP(C36,'CENTRO DE CUSTO'!$A$3:$C$536,3,0)*G36/$K$2/60,"") -> 0.105 | K36: =IF(C36<>"",VLOOKUP(C36,'CENTRO DE CUSTO'!$A$3:$C$536,3,0)*H36/60*I36,"") -> 0.46666667 | L36: =I37*H37 -> 0 | M36: 5
A37: 30 | E37: =IF(D37="","",VLOOKUP(D37,'GRUPO MÁQUINA 2025'!A4:B402,2,0)) | J37: =IF(C37<>"",VLOOKUP(C37,'CENTRO DE CUSTO'!$A$3:$C$536,3,0)*G37/$K$2/60,"") | K37: =IF(C37<>"",VLOOKUP(C37,'CENTRO DE CUSTO'!$A$3:$C$536,3,0)*H37/60*I37,"") | L37: =I38*H38 -> 0 | M37: 6
A38: 40 | B38: CORTAR EM LASER | C38: 370 | D38: 348-004 | E38: =IF(D38="","",VLOOKUP(D38,'GRUPO MÁQUINA 2025'!A5:B403,2,0)) -> MAQUINA CORTE LASER 2D GWEIKE | I38: 1 | J38: =IF(C38<>"",VLOOKUP(C38,'CENTRO DE CUSTO'!$A$3:$C$536,3,0)*G38/$K$2/60,"") -> 0 | K38: =IF(C38<>"",VLOOKUP(C38,'CENTRO DE CUSTO'!$A$3:$C$536,3,0)*H38/60*I38,"") -> 0 | L38: =I39*H39 -> 0 | M38: 7
A39: 50 | B39: DOBRAR PECA | C39: 359 | D39: 303-003 | E39: =IF(D39="","",VLOOKUP(D39,'GRUPO MÁQUINA 2025'!A6:B404,2,0)) -> DOBRADEIRA CNC 160 TN - YAWEI | I39: 1 | J39: =IF(C39<>"",VLOOKUP(C39,'CENTRO DE CUSTO'!$A$3:$C$536,3,0)*G39/$K$2/60,"") -> 0 | K39: =IF(C39<>"",VLOOKUP(C39,'CENTRO DE CUSTO'!$A$3:$C$536,3,0)*H39/60*I39,"") -> 0 | L39: =I40*H40 -> 0 | M39: 8
A40: 60 | E40: =IF(D40="","",VLOOKUP(D40,'GRUPO MÁQUINA 2025'!A7:B405,2,0)) | J40: =IF(C40<>"",VLOOKUP(C40,'CENTRO DE CUSTO'!$A$3:$C$536,3,0)*G40/$K$2/60,"") | K40: =IF(C40<>"",VLOOKUP(C40,'CENTRO DE CUSTO'!$A$3:$C$536,3,0)*H40/60*I40,"") | L40: =I41*H41 -> 0
A41: 70 | B41: PINTAR PECA | C41: 345 | D41: 350-001 | E41: =IF(D41="","",VLOOKUP(D41,'GRUPO MÁQUINA 2025'!A8:B406,2,0)) -> CABINE DE PINTURA DE PECAS | I41: 1 | J41: =IF(C41<>"",VLOOKUP(C41,'CENTRO DE CUSTO'!$A$3:$C$536,3,0)*G41/$K$2/60,"") -> 0 | K41: =IF(C41<>"",VLOOKUP(C41,'CENTRO DE CUSTO'!$A$3:$C$536,3,0)*H41/60*I41,"") -> 0 | L41: =I42*H42 -> 0
A42: 80 | B42: ESTAMPAR | C42: 360 | D42: 336-001 | E42: =IF(D42="","",VLOOKUP(D42,'GRUPO MÁQUINA 2025'!A9:B407,2,0)) -> PRENSA EXC. GUTMANN 250 T (A) | I42: 1 | J42: =IF(C42<>"",VLOOKUP(C42,'CENTRO DE CUSTO'!$A$3:$C$536,3,0)*G42/$K$2/60,"") -> 0 | K42: =IF(C42<>"",VLOOKUP(C42,'CENTRO DE CUSTO'!$A$3:$C$536,3,0)*H42/60*I42,"") -> 0 | L42: =I43*H43 -> 0
A43: 90 | B43: SOLDAR PINOS | C43: 367 | D43: 305-008 | E43: =IF(D43="","",VLOOKUP(D43,'GRUPO MÁQUINA 2025'!A10:B408,2,0)) -> EQUIPAMENTO SOLDA MIG | I43: 1 | J43: =IF(C43<>"",VLOOKUP(C43,'CENTRO DE CUSTO'!$A$3:$C$536,3,0)*G43/$K$2/60,"") -> 0 | K43: =IF(C43<>"",VLOOKUP(C43,'CENTRO DE CUSTO'!$A$3:$C$536,3,0)*H43/60*I43,"") -> 0 | L43: =I44*H44 -> 0
A44: 100 | E44: =IF(D44="","",VLOOKUP(D44,'GRUPO MÁQUINA 2025'!A11:B409,2,0)) | J44: =IF(C44<>"",VLOOKUP(C44,'CENTRO DE CUSTO'!$A$3:$C$536,3,0)*G44/$K$2/60,"") | K44: =IF(C44<>"",VLOOKUP(C44,'CENTRO DE CUSTO'!$A$3:$C$536,3,0)*H44/60*I44,"") | L44: =I45*H45 -> 0
A45: 110 | B45: MONTAR CONJ | C45: 369 | D45: 351-001 | E45: =IF(D45="","",VLOOKUP(D45,'GRUPO MÁQUINA 2025'!A12:B410,2,0)) -> SETOR DE COLAGEM 1 | I45: 1 | J45: =IF(C45<>"",VLOOKUP(C45,'CENTRO DE CUSTO'!$A$3:$C$536,3,0)*G45/$K$2/60,"") -> 0 | K45: =IF(C45<>"",VLOOKUP(C45,'CENTRO DE CUSTO'!$A$3:$C$536,3,0)*H45/60*I45,"") -> 0 | L45: =I46*#REF! -> #REF!
A46: 120 | B46: SOLDAR ULTRASSOM | C46: 369 | D46: 352-007 | E46: =IF(D46="","",VLOOKUP(D46,'GRUPO MÁQUINA 2025'!A13:B411,2,0)) -> MAQ. SOLDA ULTRASSOM 1 | I46: 1 | J46: =IF(C46<>"",VLOOKUP(C46,'CENTRO DE CUSTO'!$A$3:$C$536,3,0)*G46/$K$2/60,"") -> 0 | K46: =IF(C46<>"",VLOOKUP(C46,'CENTRO DE CUSTO'!$A$3:$C$536,3,0)*H46/60*I46,"") -> 0 | L46: =I47*H46 -> 0
A47: 130 | B47: PINTAR PECA | C47: 323 | D47: 323M | E47: =IF(D47="","",VLOOKUP(D47,'GRUPO MÁQUINA 2025'!A14:B412,2,0)) -> TUNEL DE PINTURA | I47: 1 | J47: =IF(C47<>"",VLOOKUP(C47,'CENTRO DE CUSTO'!$A$3:$C$536,3,0)*G47/$K$2/60,"") -> 0 | K47: =IF(C47<>"",VLOOKUP(C47,'CENTRO DE CUSTO'!$A$3:$C$536,3,0)*H47/60*I47,"") -> 0 | L47: =I48*H48 -> 0
A48: 140 | E48: =IF(D48="","",VLOOKUP(D48,'GRUPO MÁQUINA 2025'!A15:B413,2,0)) | J48: =IF(C48<>"",VLOOKUP(C48,'CENTRO DE CUSTO'!$A$3:$C$536,3,0)*G48/$K$2/60,"") | K48: =IF(C48<>"",VLOOKUP(C48,'CENTRO DE CUSTO'!$A$3:$C$536,3,0)*H48/60*I48,"") | L48: =I49*H49 -> 0
A49: 150 | E49: =IF(D49="","",VLOOKUP(D49,'GRUPO MÁQUINA 2025'!A16:B414,2,0)) | J49: =IF(C49<>"",VLOOKUP(C49,'CENTRO DE CUSTO'!$A$3:$C$536,3,0)*G49/$K$2/60,"") | K49: =IF(C49<>"",VLOOKUP(C49,'CENTRO DE CUSTO'!$A$3:$C$536,3,0)*H49/60*I49,"")
A50: SOMATÓRIO DOS VALORES REFERENTES A MÃO-DE-OBRA.............................................. | J50: =SUM(J35:J49) -> 0.21 | K50: =SUM(K35:K49) -> 1.1666667
A52: CUSTO DA PEÇA........ | K52: =K22+K30+K50+J50 -> 2.5462667
A54: ESTRUTURA DO FERRAMENTAL / GABARITO / RACK
A55: QUANT. | B55: DESCRIÇÃO DO FERRAMENTAL | E55: VALORES | F55: CONFECÇÃO | H55: ORÇADO COM: | J55: PRAZO P/ LIBERAÇÃO
F56: INT | G56: EXT
A64: SOMATÓRIO DOS VALORES REFERENTES AO FERRAMENTAL................................................................ | K64: =SUM(E57:E63) -> 0
A66: ENGENHARIA DA QUALIDADE | D66: TIPO DE ACABAMENTO SUPERFICIAL
A67: Nº OPER. | B67: DESCRIÇÃO DO ACABAMENTO | D67: COMPONENTE | E67: OPERAÇÃO | H67: OUTROS | I67: Nº HOMENS | K67: TEMPO (Pc/H)
E68: INT | F68: EXT
A73: ENGENHARIA DA QUALIDADE | D73: MÉTODOS DE CONTROLE
A74: ENSAIOS NECESSÁRIOS | D74: SETOR | E74: SISTEMA | H74: DESCRIÇÃO | K74: VALOR R$
E75: QS | F75: ISO
A79: SOMATÓRIO DOS VALORES REFERENTES A ENSAIOS................................................................ | K79: =SUM(K76:K78) -> 0
A81: OBSERVAÇÕES

Sheet ORÇAMENTO MOLDAGEM
A4: Cor | B4: Espessura | C4: Tamanho do blank (mm) | D4: Largura (matéria-prima) | E4: Comprimento (matéria-prima) | F4: Largura (processo) | G4: Comprimento (processo) | H4: Espessura | I4: Densidade | J4: Pçs/ chapa | K4: Perímetro (m) | L4: Preparação Moldar | M4: Tempo moldar (min) | N4: Tempo destacar (min) | O4: Tempo recortar (min) | P4: Tempo acabamento (min)
N5: 0.25 | O5: 0.5 | P5: 0.9
A6: ECO1 | B6: 4 | C6: 443 x 320 | D6: =LEFT(C6,4)/1000 -> 0.443 | E6: =RIGHT(C6,4)/1000 -> 0.32 | F6: =(LEFT(C6,4)/1000) -> 0.443 | G6: =(RIGHT(C6,4)/1000) -> 0.32 | H6: =B6/1000 -> 0.004 | I6: 1060 | J6: 1 | K6: =((2*F6)+(2*G6)) -> 1.526 | L6: =IFERROR(0.1*M6,"") -> 0.575 | M6: =IFERROR(5.75/J6,"") -> 5.75 | N6: =IFERROR((K6*$N$5),"") -> 0.3815 | O6: =IFERROR((K6*$O$5),"") -> 0.763 | P6: =IFERROR((K6*$P$5),"") -> 1.3734
A7: BRANCO GEADA | B7: 6 | C7: 405 X 406 | D7: =LEFT(C7,4)/1000 -> 0.405 | E7: =RIGHT(C7,4)/1000 -> 0.406 | F7: =(LEFT(C7,4)/1000) -> 0.405 | G7: =(RIGHT(C7,4)/1000) -> 0.406 | H7: =B7/1000 -> 0.006 | I7: 1060 | J7: =IF((ROUNDDOWN((2.7/E7),0)*ROUNDDOWN((1.7/D7),0))>(ROUNDDOWN((1.7/E7),0)*ROUNDDOWN((2.7/D7),0)),(ROUNDDOWN((2.7/E7),0)*ROUNDDOWN((1.7/D7),0)),(ROUNDDOWN((1.7/E7),0)*ROUNDDOWN((2.7/D7),0))) -> 24 | K7: =((2*F7)+(2*G7)) -> 1.622 | L7: =IFERROR(0.1*M7,"") -> 0.023958333 | M7: =IFERROR(5.75/J7,"") -> 0.23958333 | N7: =IFERROR((K7*$N$5),"") -> 0.4055 | O7: =IFERROR((K7*$O$5),"") -> 0.811 | P7: =IFERROR((K7*$P$5),"") -> 1.4598
A9: FICHA DE ORÇAMENTO
A10: DESCRIÇÃO DA PEÇA: | F10: CÓDIGO / DESENHO: | H10: - | J10: LOTE ECONÔMICO: | K10: 100
A11: ESTRUTURA DE PRODUTO
A12: CÓD. MATERIAL | B12: DESCRIÇÃO DOS COMPONENTES | E12: QUANTIDADE | F12: UN | G12: PREÇO ( R$ ) | I12: OBSERVAÇÃO | K12: TOTAL R$
F14: KG | K14: =E14*G14 -> 0
A15: 101136000 | B15: =IF(A15="","",VLOOKUP(A15,'[2]Dados MSQUERY Texto 18.02.2014'!$A$1:$D$65532,2,FALSE)) -> ADESIVO ESTRUTURAL METACRILATO ARALDITE | F15: KG | G15: 128.51 | K15: =E15*G15 -> 0
A16: 101137000 | B16: =IF(A16="","",VLOOKUP(A16,'[2]Dados MSQUERY Texto 18.02.2014'!$A$1:$D$65532,2,FALSE)) -> ATIVADOR P/ ADESIVO ESTRUTURAL METACRILATO | F16: KG | G16: 128.51 | K16: =E16*G16 -> 0
B17: =IF(A17="","",VLOOKUP(A17,'[2]Dados MSQUERY Texto 18.02.2014'!$A$1:$D$65532,2,FALSE)) | F17: =IF(B17="","",VLOOKUP(A17,'[2]Dados MSQUERY Texto 18.02.2014'!$A$1:$D$65532,4,FALSE)) | K17: =E17*G17 -> 0
A18: SOMATÓRIO DOS VALORES REFERENTES A MATÉRIA-PRIMA................................................ | K18: =SUM(K14:K17) -> 0
A20: OPERAÇÕES EXTERNAS (TERCEIROS)
A21: CÓDIGO | B21: DESCRIÇÃO | C21: QUANTIDADE | D21: UN | E21: FORNECEDOR SERVIÇO | H21: OBSERVAÇÃO | J21: PREÇO UNIT. (R$) | K21: R$
K23: =J23*C23 -> 0
K24: =J24*C24 -> 0
K25: =J25*C25 -> 0
A26: SOMATÓRIO DOS VALORES REFERENTES A OPERAÇÃO EXTERNA (TERCEIROS).............................................. | K26: =SUM(K23:K25) -> 0
A28: PROCESSO DE FABRICAÇÃO
A29: Nº OPERAÇÃO | B29: DESCRIÇÃO DA OPERAÇÃO | C29: CENTRO CUSTO | D29: GRUPO MÁQUINA | E29: DESCRIÇÃO GRUPO MÁQUINA | G29: SET-UP (MINUTOS) | H29: TEMPO OPERAÇÃO (MINUTOS) | I29: Nº DE HOMENS | J29: R$ (SET-UP) | K29: R$ (TEMPO OPERAÇÃO) | M29: 1
M30: 2
A31: 10 | B31: MOLDAR PEÇA | C31: 368 | D31: 343A | E31: =IF(D31="","",VLOOKUP(D31,'[2]GRUPO MÁQUINA 2025'!A2:B399,2,0)) -> MÁQ. TERMO FORMAGEM (A) MARCOPOLO | G31: =L7 -> 0.023958333 | H31: =M7 -> 0.23958333 | I31: 1 | J31: =IF(C31<>"",VLOOKUP(C31,'[2]CENTRO DE CUSTO'!$A$3:$C$536,3,0)*G31/$K$10/60,"") -> 0.00100625 | K31: =IF(C31<>"",VLOOKUP(C31,'CENTRO DE CUSTO'!$A$3:$C$536,3,0)*H31/60*I31,"") -> 1.00625 | L31: =I31*H31 -> 0.23958333 | M31: 3
A32: 20 | B32: DESTACAR PEÇA | C32: 369 | D32: 339-014 | E32: =IF(D32="","",VLOOKUP(D32,'[2]GRUPO MÁQUINA 2025'!A3:B400,2,0)) -> DESTACAR PEÇA 1 | H32: =N7 -> 0.4055 | I32: 1 | J32: =IF(C32<>"",VLOOKUP(C32,'[2]CENTRO DE CUSTO'!$A$3:$C$536,3,0)*G32/$K$10/60,"") -> 0 | K32: =IF(C32<>"",VLOOKUP(C32,'CENTRO DE CUSTO'!$A$3:$C$536,3,0)*H32/60*I32,"") -> 0.709625 | L32: =I32*H32 -> 0.4055 | M32: 4
A33: 30 | B33: RECORTAR PEÇA | C33: 369 | D33: 339-015 | E33: =IF(D33="","",VLOOKUP(D33,'[2]GRUPO MÁQUINA 2025'!A4:B401,2,0)) -> CORTE TUPIA | H33: =O7 -> 0.811 | I33: 1 | J33: =IF(C33<>"",VLOOKUP(C33,'[2]CENTRO DE CUSTO'!$A$3:$C$536,3,0)*G33/$K$10/60,"") -> 0 | K33: =IF(C33<>"",VLOOKUP(C33,'CENTRO DE CUSTO'!$A$3:$C$536,3,0)*H33/60*I33,"") -> 1.41925 | L33: =I33*H33 -> 0.811 | M33: 5
A34: 40 | B34: DAR ACABAMENTO | C34: 369 | D34: 339-013 | E34: =IF(D34="","",VLOOKUP(D34,'[2]GRUPO MÁQUINA 2025'!A5:B402,2,0)) -> LIXADEIRA 1 | H34: =P7 -> 1.4598 | I34: 1 | J34: =IF(C34<>"",VLOOKUP(C34,'[2]CENTRO DE CUSTO'!$A$3:$C$536,3,0)*G34/$K$10/60,"") -> 0 | K34: =IF(C34<>"",VLOOKUP(C34,'CENTRO DE CUSTO'!$A$3:$C$536,3,0)*H34/60*I34,"") -> 2.55465 | L34: =I34*H34 -> 1.4598 | M34: 6
A35: 50 | B35: MONTAR CONJUNTO | C35: 369 | D35: 351-003 | E35: =IF(D35="","",VLOOKUP(D35,'[2]GRUPO MÁQUINA 2025'!A6:B403,2,0)) -> MON/COL 1 - MARCOPOLO | H35: 8 | I35: 1 | J35: =IF(C35<>"",VLOOKUP(C35,'[2]CENTRO DE CUSTO'!$A$3:$C$536,3,0)*G35/$K$10/60,"") -> 0 | K35: =IF(C35<>"",VLOOKUP(C35,'CENTRO DE CUSTO'!$A$3:$C$536,3,0)*H35/60*I35,"") -> 14 | L35: =I35*H35 -> 8 | M35: 7
A36: 60 | E36: =IF(D36="","",VLOOKUP(D36,'[2]GRUPO MÁQUINA 2025'!A7:B404,2,0)) | J36: =IF(C36<>"",VLOOKUP(C36,'[2]CENTRO DE CUSTO'!$A$3:$C$536,3,0)*G36/$K$10/60,"") | K36: =IF(C36<>"",VLOOKUP(C36,'CENTRO DE CUSTO'!$A$3:$C$536,3,0)*H36/60*I36,"") | L36: =I36*H36 -> 0 | M36: 8
A37: 70 | E37: =IF(D37="","",VLOOKUP(D37,'[2]GRUPO MÁQUINA 2025'!A8:B405,2,0)) | J37: =IF(C37<>"",VLOOKUP(C37,'[2]CENTRO DE CUSTO'!$A$3:$C$536,3,0)*G37/$K$10/60,"") | K37: =IF(C37<>"",VLOOKUP(C37,'CENTRO DE CUSTO'!$A$3:$C$536,3,0)*H37/60*I37,"") | L37: =I37*H37 -> 0
A38: 80 | E38: =IF(D38="","",VLOOKUP(D38,'[2]GRUPO MÁQUINA 2025'!A9:B406,2,0)) | J38: =IF(C38<>"",VLOOKUP(C38,'[2]CENTRO DE CUSTO'!$A$3:$C$536,3,0)*G38/$K$10/60,"") | K38: =IF(C38<>"",VLOOKUP(C38,'CENTRO DE CUSTO'!$A$3:$C$536,3,0)*H38/60*I38,"") | L38: =I38*H38 -> 0
A39: 90 | E39: =IF(D39="","",VLOOKUP(D39,'[2]GRUPO MÁQUINA 2025'!A10:B407,2,0)) | J39: =IF(C39<>"",VLOOKUP(C39,'[2]CENTRO DE CUSTO'!$A$3:$C$536,3,0)*G39/$K$10/60,"") | K39: =IF(C39<>"",VLOOKUP(C39,'CENTRO DE CUSTO'!$A$3:$C$536,3,0)*H39/60*I39,"") | L39: =I39*H39 -> 0
A40: 100 | E40: =IF(D40="","",VLOOKUP(D40,'[2]GRUPO MÁQUINA 2025'!A11:B408,2,0)) | J40: =IF(C40<>"",VLOOKUP(C40,'[2]CENTRO DE CUSTO'!$A$3:$C$536,3,0)*G40/$K$10/60,"") | K40: =IF(C40<>"",VLOOKUP(C40,'CENTRO DE CUSTO'!$A$3:$C$536,3,0)*H40/60*I40,"") | L40: =I40*H40 -> 0
A41: 110 | E41: =IF(D41="","",VLOOKUP(D41,'[2]GRUPO MÁQUINA 2025'!A12:B409,2,0)) | J41: =IF(C41<>"",VLOOKUP(C41,'[2]CENTRO DE CUSTO'!$A$3:$C$536,3,0)*G41/$K$10/60,"") | K41: =IF(C41<>"",VLOOKUP(C41,'CENTRO DE CUSTO'!$A$3:$C$536,3,0)*H41/60*I41,"") | L41: =I41*H41 -> 0
A42: 120 | E42: =IF(D42="","",VLOOKUP(D42,'[2]GRUPO MÁQUINA 2025'!A13:B410,2,0)) | J42: =IF(C42<>"",VLOOKUP(C42,'[2]CENTRO DE CUSTO'!$A$3:$C$536,3,0)*G42/$K$10/60,"") | K42: =IF(C42<>"",VLOOKUP(C42,'CENTRO DE CUSTO'!$A$3:$C$536,3,0)*H42/60*I42,"") | L42: =I42*H42 -> 0
A43: 130 | B43: MOLDAR PEÇA | C43: 368 | D43: 343A | E43: =IF(D43="","",VLOOKUP(D43,'[2]GRUPO MÁQUINA 2025'!A14:B411,2,0)) -> MÁQ. TERMO FORMAGEM (A) MARCOPOLO | I43: 1 | J43: =IF(C43<>"",VLOOKUP(C43,'[2]CENTRO DE CUSTO'!$A$3:$C$536,3,0)*G43/$K$10/60,"") -> 0 | K43: =IF(C43<>"",VLOOKUP(C43,'CENTRO DE CUSTO'!$A$3:$C$536,3,0)*H43/60*I43,"") -> 0 | L43: =I43*H43 -> 0
A44: 140 | E44: =IF(D44="","",VLOOKUP(D44,'[2]GRUPO MÁQUINA 2025'!A15:B412,2,0)) | J44: =IF(C44<>"",VLOOKUP(C44,'[2]CENTRO DE CUSTO'!$A$3:$C$536,3,0)*G44/$K$10/60,"") | K44: =IF(C44<>"",VLOOKUP(C44,'CENTRO DE CUSTO'!$A$3:$C$536,3,0)*H44/60*I44,"") | L44: =I44*H44 -> 0
A45: 150 | E45: =IF(D45="","",VLOOKUP(D45,'[2]GRUPO MÁQUINA 2025'!A16:B413,2,0)) | J45: =IF(C45<>"",VLOOKUP(C45,'[2]CENTRO DE CUSTO'!$A$3:$C$536,3,0)*G45/$K$10/60,"") | K45: =IF(C45<>"",VLOOKUP(C45,'CENTRO DE CUSTO'!$A$3:$C$536,3,0)*H45/60*I45,"") | L45: =I45*H45 -> 0
A46: SOMATÓRIO DOS VALORES REFERENTES A MÃO-DE-OBRA.............................................. | J46: =SUM(J31:J45) -> 0.00100625 | K46: =SUM(K31:K45) -> 19.689775
A48: CUSTO DA PEÇA........ | K48: =K18+K26+K46+J46 -> 19.690781
A50: ESTRUTURA DO FERRAMENTAL / GABARITO / RACK
A51: QUANT. | B51: DESCRIÇÃO DO FERRAMENTAL | E51: VALORES | F51: CONFECÇÃO | H51: ORÇADO COM: | J51: PRAZO P/ LIBERAÇÃO
F52: INT | G52: EXT
M53: CHARLES
M54: EDERSON
M55: ILDO
M56: ISAAC
M57: OUTROS
M58: TOSO
M59: VALDIR
A60: SOMATÓRIO DOS VALORES REFERENTES AO FERRAMENTAL................................................................ | K60: =SUM(E53:E59) -> 0
A62: ENGENHARIA DA QUALIDADE | D62: TIPO DE ACABAMENTO SUPERFICIAL
A63: Nº OPER. | B63: DESCRIÇÃO DO ACABAMENTO | D63: COMPONENTE | E63: OPERAÇÃO | H63: OUTROS | I63: Nº HOMENS | K63: TEMPO (Pc/H)
E64: INT | F64: EXT
A69: ENGENHARIA DA QUALIDADE | D69: MÉTODOS DE CONTROLE
A70: ENSAIOS NECESSÁRIOS | D70: SETOR | E70: SISTEMA | H70: DESCRIÇÃO | K70: VALOR R$
E71: QS | F71: ISO
A75: SOMATÓRIO DOS VALORES REFERENTES A ENSAIOS................................................................ | K75: =SUM(K72:K74) -> 0
A77: OBSERVAÇÕES

Sheet ORÇAMENTO PINTURA
A1: Código Amalcaburio | B1: Código Marcopolo | C1: Comprimento (mm) | D1: Largura (mm) | E1: Área (mm²) | F1: Área (m2) | G1: Tinta por mm ² | H1: Quantidade de tinta (mL) | I1: Catalizador (L) | J1: Tempo pintura (mm² por min) | K1: Tempo Pintura | L1: Cor | M1: Custo pintura PARA UM LADO DA PEÇA | O1: Custo pintura PARA DOIS LADO DA PEÇA | P1: Código Amalcaburio
A2: 802914000 | B2: 11276419 | C2: 571 | D2: 406 | E2: =PRODUCT(C2:D2) -> 231826 | G2: 3.26e-07 | H2: =E2*G2*1.89 -> 0.14283727 | I2: =H2/8 -> 0.017854659 | J2: 1.8181e-05 | K2: =E2*J2 -> 4.2148285 | L2: PRETO FOSCO | O2: 105479000 | P2: PRETO FOSCO
A3: 803402000 | B3: 11107694 | C3: 495 | D3: 395 | E3: =PRODUCT(C3:D3) -> 195525 | G3: 3.26e-07 | H3: =E3*G3*1.89 -> 0.12047077 | I3: =H3/8 -> 0.015058847 | J3: 1.8181e-05 | K3: =E3*J3 -> 3.55484 | L3: PRETO FOSCO
A4: 803406000 | B4: 10870475 | C4: 525 | D4: 361 | E4: =PRODUCT(C4:D4) -> 189525 | G4: 3.26e-07 | H4: =E4*G4*1.89 -> 0.11677393 | I4: =H4/8 -> 0.014596742 | J4: 1.8181e-05 | K4: =E4*J4 -> 3.445754 | L4: PRETO FOSCO
A5: 803455000 | B5: 10920424 | C5: 470 | D5: 360 | E5: =PRODUCT(C5:D5) -> 169200 | G5: 3.26e-07 | H5: =E5*G5 -> 0.0551592 | I5: =H5/8 -> 0.0068949 | J5: 1.8181e-05 | K5: =E5*J5 -> 3.0762252 | L5: PRETO FOSCO
A6: 803458000 | B6: 10738417 | C6: 569 | D6: 400 | E6: =PRODUCT(C6:D6) -> 227600 | G6: 3.26e-07 | H6: =E6*G6*1.89 -> 0.14023346 | I6: =H6/8 -> 0.017529183 | J6: 1.8181e-05 | K6: =E6*J6 -> 4.1379956 | L6: PRETO FOSCO
A7: 803465000 | B7: 10961664 | C7: 394 | D7: 349 | E7: =PRODUCT(C7:D7) -> 137506 | G7: 3.26e-07 | H7: =E7*G7 -> 0.044826956 | I7: =H7/8 -> 0.0056033695 | J7: 1.8181e-05 | K7: =E7*J7 -> 2.4999966 | L7: PRETO FOSCO
A8: 803473000 | B8: 10780075 | C8: 491 | D8: 380 | E8: =PRODUCT(C8:D8) -> 186580 | G8: 3.26e-07 | H8: =E8*G8*1.89 -> 0.1149594 | I8: =H8/8 -> 0.014369925 | J8: 1.8181e-05 | K8: =E8*J8 -> 3.392211 | L8: PRETO FOSCO
A9: 803474000 | B9: 11030580 | C9: 570 | D9: 354 | E9: =PRODUCT(C9:D9) -> 201780 | G9: 3.26e-07 | H9: =E9*G9*1.89 -> 0.12432473 | I9: =H9/8 -> 0.015540591 | J9: 1.8181e-05 | K9: =E9*J9 -> 3.6685622 | L9: PRETO FOSCO
A10: 803484000 | B10: 10998537 | C10: 464 | D10: 354 | E10: =PRODUCT(C10:D10) -> 164256 | G10: 3.26e-07 | H10: =E10*G10*1.89 -> 0.10120469 | I10: =H10/8 -> 0.012650586 | J10: 1.8181e-05 | K10: =E10*J10 -> 2.9863383 | L10: PRETO FOSCO
A11: 803504000 | B11: 11116985 | C11: 504 | D11: 353 | E11: =PRODUCT(C11:D11) -> 177912 | G11: 3.26e-07 | H11: =E11*G11*1.89 -> 0.1096187 | I11: =H11/8 -> 0.013702337 | J11: 1.8181e-05 | K11: =E11*J11 -> 3.2346181 | L11: PRETO FOSCO
A12: 803510000 | B12: 10993938 | C12: 555 | D12: 350 | E12: =PRODUCT(C12:D12) -> 194250 | G12: 3.26e-07 | H12: =E12*G12*1.89 -> 0.11968519 | I12: =H12/8 -> 0.014960649 | J12: 1.8181e-05 | K12: =E12*J12 -> 3.5316593 | L12: PRETO FOSCO
A13: 803535000 | B13: 11116987 | C13: 502 | D13: 238 | E13: =PRODUCT(C13:D13) -> 119476 | G13: 3.26e-07 | H13: =E13*G13*1.89 -> 0.073613943 | I13: =H13/8 -> 0.0092017428 | J13: 1.8181e-05 | K13: =E13*J13 -> 2.1721932 | L13: PRETO FOSCO
A14: 803537000 | B14: 10916599 | C14: 426 | D14: 355 | E14: =PRODUCT(C14:D14) -> 151230 | G14: 3.26e-07 | H14: =E14*G14*1.89 -> 0.093178852 | I14: =H14/8 -> 0.011647357 | J14: 1.8181e-05 | K14: =E14*J14 -> 2.7495126 | L14: PRETO FOSCO
A15: 803585000 | B15: 10373754 | C15: 511 | D15: 385 | E15: =PRODUCT(C15:D15) -> 196735 | G15: 3.26e-07 | H15: =E15*G15*1.89 -> 0.1212163 | I15: =H15/8 -> 0.015152038 | J15: 1.8181e-05 | K15: =E15*J15 -> 3.576839 | L15: PRETO FOSCO
A16: 803591000 | B16: 10993939 | C16: 500 | D16: 363 | E16: =PRODUCT(C16:D16) -> 181500 | G16: 3.26e-07 | H16: =E16*G16*1.89 -> 0.11182941 | I16: =H16/8 -> 0.013978676 | J16: 1.8181e-05 | K16: =E16*J16 -> 3.2998515 | L16: PRETO FOSCO
A17: 803642000 | B17: 10943061 | C17: 491 | D17: 352 | E17: =PRODUCT(C17:D17) -> 172832 | G17: 3.26e-07 | H17: =E17*G17*1.89 -> 0.10648871 | I17: =H17/8 -> 0.013311089 | J17: 1.8181e-05 | K17: =E17*J17 -> 3.1422586 | L17: PRETO FOSCO
A18: 803647000 | B18: 11196630 | C18: 543 | D18: 370 | E18: =PRODUCT(C18:D18) -> 200910 | G18: 3.26e-07 | H18: =E18*G18*1.89 -> 0.12378869 | I18: =H18/8 -> 0.015473586 | J18: 1.8181e-05 | K18: =E18*J18 -> 3.6527447 | L18: PRETO FOSCO
A19: 803683000 | B19: 10651364 | C19: 325 | D19: 230 | E19: =PRODUCT(C19:D19) -> 74750 | G19: 3.26e-07 | H19: =E19*G19*1.89 -> 0.046056465 | I19: =H19/8 -> 0.0057570581 | J19: 1.8181e-05 | K19: =E19*J19 -> 1.3590298 | L19: PRETO FOSCO
... A21: 803736000 | B21: 10419797 | C21: 85 | D21: 85 | E21: =PRODUCT(C21:D21) -> 7225 | G21: 3.26e-07 | H21: =E21*G21*1.89 -> 0.0044516115 | I21: =H21/8 -> 0.00055645144 | J21: 1.8181e-05 | K21: =E21*J21 -> 0.13135773 | L21: CINZA TITÂNIO
B22: 10227064 | C22: 520 | D22: 372 | E22: =PRODUCT(C22:D22) -> 193440 | G22: 3.26e-07 | H22: =E22*G22*1.89 -> 0.11918612 | I22: =H22/8 -> 0.014898265 | J22: 1.8181e-05 | K22: =E22*J22 -> 3.5169326 | L22: PRETO FOSCO
A23: 803924000 | B23: 10454751 | C23: 404 | D23: 397 | E23: =PRODUCT(C23:D23) -> 160388 | G23: 3.26e-07 | H23: =E23*G23*1.89 -> 0.098821462 | I23: =H23/8 -> 0.012352683 | J23: 1.8181e-05 | K23: =E23*J23 -> 2.9160142 | L23: PRETO FOSCO
A24: 803761000 | B24: 10451899 | C24: 669 | D24: 454 | E24: =PRODUCT(C24:D24) -> 303726 | G24: 3.26e-07 | H24: =E24*G24*1.89 -> 0.18713774 | I24: =H24/8 -> 0.023392217 | J24: 1.8181e-05 | K24: =E24*J24 -> 5.5220424 | L24: PRETO FOSCO
B25: 10554264 | C25: 375 | D25: 337 | E25: =PRODUCT(C25:D25) -> 126375 | G25: 3.26e-07 | H25: =E25*G25*1.89 -> 0.077864692 | I25: =H25/8 -> 0.0097330866 | J25: 1.8181e-05 | K25: =E25*J25 -> 2.2976239 | L25: PRETO FOSCO
A26: 803781000 | B26: 10657376 | C26: 550 | D26: 288 | E26: =PRODUCT(C26:D26) -> 158400 | G26: 3.26e-07 | H26: =E26*G26*1.89 -> 0.097596576 | I26: =H26/8 -> 0.012199572 | J26: 1.8181e-05 | K26: =E26*J26 -> 2.8798704 | L26: PRETO FOSCO
B27: 10745341 | C27: 469 | D27: 400 | E27: =PRODUCT(C27:D27) -> 187600 | G27: 3.26e-07 | H27: =E27*G27*1.89 -> 0.11558786 | I27: =H27/8 -> 0.014448483 | J27: 1.8181e-05 | K27: =E27*J27 -> 3.4107556 | L27: PRETO FOSCO
A28: 803840000 | B28: 11031883 | C28: 564 | D28: 440 | E28: =PRODUCT(C28:D28) -> 248160 | G28: 3.26e-07 | H28: =E28*G28*1.89 -> 0.1529013 | I28: =H28/8 -> 0.019112663 | J28: 1.8181e-05 | K28: =E28*J28 -> 4.511797 | L28: PRETO FOSCO
B29: 11143262 | C29: 465 | D29: 340 | E29: =PRODUCT(C29:D29) -> 158100 | G29: 3.26e-07 | H29: =E29*G29*1.89 -> 0.097411734 | I29: =H29/8 -> 0.012176467 | J29: 1.8181e-05 | K29: =E29*J29 -> 2.8744161 | L29: PRETO FOSCO
B30: 11202216 | C30: 544 | D30: 368 | E30: =PRODUCT(C30:D30) -> 200192 | G30: 3.26e-07 | H30: =E30*G30*1.89 -> 0.1233463 | I30: =H30/8 -> 0.015418287 | J30: 1.8181e-05 | K30: =E30*J30 -> 3.6396908 | L30: PRETO FOSCO
B31: 11254144 | C31: 487 | D31: 270 | E31: =PRODUCT(C31:D31) -> 131490 | G31: 3.26e-07 | H31: =E31*G31*1.89 -> 0.081016249 | I31: =H31/8 -> 0.010127031 | J31: 1.8181e-05 | K31: =E31*J31 -> 2.3906197 | L31: PRETO FOSCO
B32: 11145112 | C32: 610 | D32: 80 | E32: =PRODUCT(C32:D32) -> 48800 | G32: 3.26e-07 | H32: =E32*G32*1.5 -> 0.0238632 | I32: =H32/8 -> 0.0029829 | J32: 1.8181e-05 | K32: =E32*J32 -> 0.8872328 | L32: PRETO BRILHO
B33: 11145113 | C33: - | D33: - | E33: 52363 | G33: 3.26e-07 | H33: =E33*G33*1.5 -> 0.025605507 | I33: =H33/8 -> 0.0032006884 | J33: 1.8181e-05 | K33: =E33*J33 -> 0.9520117 | L33: PRETO BRILHO
B34: 11269282 | C34: - | D34: - | E34: 52363 | G34: 3.26e-07 | H34: =E34*G34*1.5 -> 0.025605507 | I34: =H34/8 -> 0.0032006884 | J34: 1.8181e-05 | K34: =E34*J34 -> 0.9520117 | L34: PRETO BRILHO
B35: 11270480 | C35: 610 | D35: 80 | E35: =PRODUCT(C35:D35) -> 48800 | G35: 3.26e-07 | H35: =E35*G35*1.5 -> 0.0238632 | I35: =H35/8 -> 0.0029829 | J35: 1.8181e-05 | K35: =E35*J35 -> 0.8872328 | L35: PRETO BRILHO
B36: 11272315 | C36: - | D36: - | E36: 24566 | G36: 3.26e-07 | H36: =E36*G36*1.5 -> 0.012012774 | I36: =H36/8 -> 0.0015015968 | J36: 1.8181e-05 | K36: =E36*J36 -> 0.44663445 | L36: PRETO BRILHO
B37: 11274397 | C37: - | D37: - | E37: 46373 | G37: 3.26e-07 | H37: =E37*G37*1.5 -> 0.022676397 | I37: =H37/8 -> 0.0028345496 | J37: 1.8181e-05 | K37: =E37*J37 -> 0.84310751 | L37: PRETO BRILHO
B38: 11274398 | C38: - | D38: - | E38: 46373 | G38: 3.26e-07 | H38: =E38*G38*1.5 -> 0.022676397 | I38: =H38/8 -> 0.0028345496 | J38: 1.8181e-05 | K38: =E38*J38 -> 0.84310751 | L38: PRETO BRILHO
B39: 17284870 | C39: 310 | D39: 125 | E39: =PRODUCT(C39:D39) -> 38750 | G39: 3.26e-07 | H39: =E39*G39*1.89 -> 0.023875425 | I39: =H39/8 -> 0.0029844281 | J39: 1.8181e-05 | K39: =E39*J39 -> 0.70451375 | L39: FUNDO CINZA
A40: 803764000 | B40: 11130013 | C40: 627 | D40: 570 | E40: =PRODUCT(C40:D40) -> 357390 | G40: 3.26e-07 | H40: =E40*G40 -> 0.11650914 | I40: =H40/8 -> 0.014563642 | J40: 1.8181e-05 | K40: =E40*J40 -> 6.4977076 | L40: PRETO FOSCO
A41: 803845000 | B41: 11390746 | C41: 512 | D41: 400 | E41: =PRODUCT(C41:D41) -> 204800 | G41: 3.26e-07 | H41: =E41*G41 -> 0.0667648 | I41: =H41/8 -> 0.0083456 | J41: 1.8181e-05 | K41: =E41*J41 -> 3.7234688 | L41: PRETO FOSCO
A42: 803859000 | B42: 11411471 | C42: 511 | D42: 385 | E42: =PRODUCT(C42:D42) -> 196735 | G42: 3.26e-07 | H42: =E42*G42 -> 0.06413561 | I42: =H42/8 -> 0.0080169512 | J42: 1.8181e-05 | K42: =E42*J42 -> 3.576839 | L42: PRETO FOSCO
A43: 803866000 | B43: 11429641 | C43: 581 | D43: 325 | E43: =PRODUCT(C43:D43) -> 188825 | G43: 3.26e-07 | H43: =E43*G43 -> 0.06155695 | I43: =H43/8 -> 0.0076946187 | J43: 1.8181e-05 | K43: =E43*J43 -> 3.4330273 | L43: PRETO FOSCO
A44: 803508000 | B44: 10628586 | C44: 446 | D44: 143 | E44: =PRODUCT(C44:D44) -> 63778 | G44: 3.26e-07 | H44: =E44*G44 -> 0.020791628 | I44: =H44/8 -> 0.0025989535 | J44: 1.8181e-05 | K44: =E44*J44 -> 1.1595478 | L44: CINZA TITÂNIO
A45: 803644000 | B45: 10899633 | C45: 469 | D45: 400 | E45: =PRODUCT(C45:D45) -> 187600 | G45: 3.26e-07 | H45: =E45*G45 -> 0.0611576 | I45: =H45/8 -> 0.0076447 | J45: 1.8181e-05 | K45: =E45*J45 -> 3.4107556 | L45: PRETO FOSCO
A46: 802650000 | B46: 10983474 | C46: 1040 | D46: 184 | E46: =PRODUCT(C46:D46) -> 191360 | G46: 3.26e-07 | H46: =E46*G46 -> 0.06238336 | I46: =H46/8 -> 0.00779792 | J46: 1.8181e-05 | K46: =E46*J46 -> 3.4791162
A47: 802651000 | B47: 10983475 | C47: 1040 | D47: 184 | E47: =PRODUCT(C47:D47) -> 191360 | G47: 3.26e-07 | H47: =E47*G47 -> 0.06238336 | I47: =H47/8 -> 0.00779792 | J47: 1.8181e-05 | K47: =E47*J47 -> 3.4791162
A48: 803876000 | B48: 11442427 | C48: 412 | D48: 268 | E48: =PRODUCT(C48:D48) -> 110416 | G48: 3.26e-07 | H48: =E48*G48 -> 0.035995616 | I48: =H48/8 -> 0.004499452 | J48: 1.8181e-05 | K48: =E48*J48 -> 2.0074733
A49: 803898000 | B49: 11435582 | C49: 504 | D49: 328 | E49: =PRODUCT(C49:D49) -> 165312 | G49: 3.26e-07 | H49: =E49*G49 -> 0.053891712 | I49: =H49/8 -> 0.006736464 | J49: 1.8181e-05 | K49: =E49*J49 -> 3.0055375
A50: 803963000 | B50: 10413297 | C50: 365 | D50: 810 | E50: =PRODUCT(C50:D50) -> 295650 | G50: 3.26e-07 | H50: =E50*G50 -> 0.0963819 | I50: =H50/8 -> 0.012047737 | J50: 1.8181e-05 | K50: =E50*J50 -> 5.3752126
A51: 803974000 | B51: 11032810 | C51: 303 | D51: 346 | E51: =PRODUCT(C51:D51) -> 104838 | G51: 3.26e-07 | H51: =E51*G51 -> 0.034177188 | I51: =H51/8 -> 0.0042721485 | J51: 1.8181e-05 | K51: =E51*J51 -> 1.9060597 | L51: CINZA TITÂNIO
B52: 11662158 | C52: 169 | D52: 240 | E52: =PRODUCT(C52:D52) -> 40560 | G52: 3.26e-07 | H52: =E52*G52 -> 0.01322256 | I52: =H52/8 -> 0.00165282 | J52: 1.8181e-05 | K52: =E52*J52 -> 0.73742136 | L52: CINZA TITÂNIO
B53: 33330814 | C53: 732 | D53: 1074 | E53: =PRODUCT(C53:D53) -> 786168 | G53: 3.26e-07 | H53: =E53*G53 -> 0.25629077 | I53: =H53/8 -> 0.032036346 | J53: 1.8181e-05 | K53: =E53*J53 -> 14.29332 | L53: AZUL MP2
B54: 33330815 | C54: 729 | D54: 1075 | E54: =PRODUCT(C54:D54) -> 783675 | G54: 3.26e-07 | H54: =E54*G54 -> 0.25547805 | I54: =H54/8 -> 0.031934756 | J54: 1.8181e-05 | K54: =E54*J54 -> 14.247995 | L54: AZUL MP2
B55: 11685185 | C55: 362 | D55: 569 | E55: =PRODUCT(C55:D55) -> 205978 | G55: 3.26e-07 | H55: =E55*G55 -> 0.067148828 | J55: 1.8181e-05 | K55: =E55*J55 -> 3.744886 | L55: PRETO FOSCO
B56: 11701780 | C56: 271 | D56: 150 | E56: =PRODUCT(C56:D56) -> 40650 | G56: 3.26e-07 | H56: =E56*G56 -> 0.0132519 | J56: 1.8181e-05 | K56: =E56*J56 -> 0.73905765 | L56: PRETO FOSCO
B57: 11701759 | C57: 271 | D57: 150 | E57: =PRODUCT(C57:D57) -> 40650 | G57: 3.26e-07 | H57: =E57*G57 -> 0.0132519 | J57: 1.8181e-05 | K57: =E57*J57 -> 0.73905765 | L57: PRETO FOSCO
B58: 11701758 | C58: 271 | D58: 150 | E58: =PRODUCT(C58:D58) -> 40650 | G58: 3.26e-07 | H58: =E58*G58 -> 0.0132519 | J58: 1.8181e-05 | K58: =E58*J58 -> 0.73905765 | L58: PRETO FOSCO
B59: 11728569 | C59: 380 | D59: 491 | E59: =PRODUCT(C59:D59) -> 186580 | G59: 3.26e-07 | H59: =E59*G59 -> 0.06082508 | J59: 1.8181e-05 | K59: =E59*J59 -> 3.392211 | L59: PRETO FOSCO
B60: 11739684 | C60: 445 | D60: 331 | E60: =PRODUCT(C60:D60) -> 147295 | G60: 3.26e-07 | H60: =E60*G60 -> 0.04801817 | J60: 1.8181e-05 | K60: =E60*J60 -> 2.6779704 | L60: PRETO FOSCO
B61: 11809613 | C61: 369 | D61: 370 | E61: =PRODUCT(C61:D61) -> 136530 | G61: 3.26e-07 | H61: =E61*G61 -> 0.04450878 | J61: 1.8181e-05 | K61: =E61*J61 -> 2.4822519 | L61: PRETO FOSCO
B62: 11786425 | C62: 50 | D62: 531 | E62: =PRODUCT(C62:D62) -> 26550 | G62: 3.26e-07 | H62: =E62*G62 -> 0.0086553 | J62: 1.8181e-05 | K62: =E62*J62 -> 0.48270555 | L62: PRETO BRILHO
B63: 11750416 | C63: 304 | D63: 726 | E63: =PRODUCT(C63:D63) -> 220704 | G63: 3.26e-07 | H63: =E63*G63 -> 0.071949504 | J63: 1.8181e-05 | K63: =E63*J63 -> 4.0126194 | L63: PRETO BRILHO
B64: 11750521 | C64: 304 | D64: 726 | E64: =PRODUCT(C64:D64) -> 220704 | G64: 3.26e-07 | H64: =E64*G64 -> 0.071949504 | J64: 1.8181e-05 | K64: =E64*J64 -> 4.0126194 | L64: PRETO BRILHO
B65: 11865193 | C65: 386 | D65: 729 | E65: =PRODUCT(C65:D65) -> 281394 | G65: 3.26e-07 | H65: =E65*G65 -> 0.091734444 | J65: 1.8181e-05 | K65: =E65*J65 -> 5.1160243 | L65: PRETO BRILHO
A66: 805290000 | B66: 11750331 | C66: 270 | D66: 500 | E66: =PRODUCT(C66:D66) -> 135000 | G66: 3.26e-07 | H66: =E66*G66 -> 0.04401 | J66: 1.8181e-05 | K66: =E66*J66 -> 2.454435 | L66: PRETO FOSCO
A67: 806213000 | B67: 11815322 | C67: 233 | D67: 460 | E67: =PRODUCT(C67:D67) -> 107180 | G67: 3.26e-07 | H67: =E67*G67 -> 0.03494068 | J67: 1.8181e-05 | K67: =E67*J67 -> 1.9486396 | L67: PRETO FOSCO
A68: 806250000 | B68: 11886330 | C68: 345 | D68: 637 | E68: =PRODUCT(C68:D68) -> 219765 | G68: 3.26e-07 | H68: =E68*G68 -> 0.07164339 | J68: 1.8181e-05 | K68: =E68*J68 -> 3.9955475 | L68: PRETO FOSCO
A69: 804743000 | B69: 10327227 | C69: 185 | D69: 594 | E69: =PRODUCT(C69:D69) -> 109890 | G69: 3.26e-07 | H69: =E69*G69 -> 0.03582414 | J69: 1.8181e-05 | K69: =E69*J69 -> 1.9979101 | L69: CINZA TITÂNIO
A70: 706237020 | B70: 11928692 | C70: 95 | D70: 250 | E70: =PRODUCT(C70:D70) -> 23750 | G70: 3.26e-07 | H70: =E70*G70 -> 0.0077425 | J70: 1.8181e-05 | K70: =E70*J70 -> 0.43179875 | L70: PRETO FOSCO
A71: 706237010 | B71: 11928673 | C71: 96 | D71: 256 | E71: =PRODUCT(C71:D71) -> 24576 | G71: 3.26e-07 | H71: =E71*G71 -> 0.008011776 | J71: 1.8181e-05 | K71: =E71*J71 -> 0.44681626 | L71: PRETO FOSCO
A72: 806277000 | B72: 10815371 | C72: 390 | D72: 420 | E72: =PRODUCT(C72:D72) -> 163800 | G72: 3.26e-07 | H72: =E72*G72 -> 0.0533988 | J72: 1.8181e-05 | K72: =E72*J72 -> 2.9780478 | L72: PRETO FOSCO
A73: 805794000 | B73: 11605368 | C73: 311 | D73: 338 | E73: =PRODUCT(C73:D73) -> 105118 | G73: 3.26e-07 | H73: =E73*G73 -> 0.034268468 | J73: 1.8181e-05 | K73: =E73*J73 -> 1.9111504 | L73: PRETO BRILHO
A74: 806304000 | B74: 11116989 | C74: 306 | D74: 504 | E74: =PRODUCT(C74:D74) -> 154224 | G74: 3.26e-07 | H74: =E74*G74 -> 0.050277024 | J74: 1.8181e-05 | K74: =E74*J74 -> 2.8039465 | L74: PRETO FOSCO
A75: 806306000 | B75: 11943351 | C75: 163 | D75: 183 | E75: =PRODUCT(C75:D75) -> 29829 | G75: 3.26e-07 | H75: =E75*G75 -> 0.009724254 | J75: 1.8181e-05 | K75: =E75*J75 -> 0.54232105 | L75: PRETO FOSCO
A76: 806609000 | B76: 11951908 | C76: 233 | D76: 460 | E76: =PRODUCT(C76:D76) -> 107180 | G76: 3.26e-07 | H76: =E76*G76 -> 0.03494068 | J76: 1.8181e-05 | K76: =E76*J76 -> 1.9486396 | L76: PRETO FOSCO
A77: 806686000 | B77: 11977657 | C77: 406 | D77: 570 | E77: =PRODUCT(C77:D77) -> 231420 | G77: 3.26e-07 | H77: =E77*G77 -> 0.07544292 | J77: 1.8181e-05 | K77: =E77*J77 -> 4.207447 | L77: PRETO FOSCO
... A86: 802557000 | B86: 12681547 | C86: 311 | D86: 338 | E86: =PRODUCT(C86:D86) -> 105118 | G86: 3.26e-07 | H86: =E86*G86 -> 0.034268468 | J86: 1.8181e-05 | K86: =E86*J86 -> 1.9111504 | L86: PRETO FOSCO
A87: 802952000 | B87: 11861268 | C87: 525 | D87: 200 | E87: =PRODUCT(C87:D87) -> 105000 | G87: 3.26e-07 | H87: =E87*G87 -> 0.03423 | J87: 1.8181e-05 | K87: =E87*J87 -> 1.909005 | L87: PRIMER | M87: (106594000 - 30% )- (106613000 - 60% )- (300246000 - 10% ) - (PROPORÇÃO)
A88: 802953000 | B88: 11861269 | C88: 525 | D88: 200 | E88: =PRODUCT(C88:D88) -> 105000 | G88: 3.26e-07 | H88: =E88*G88 -> 0.03423 | J88: 1.8181e-05 | K88: =E88*J88 -> 1.909005 | L88: PRIMER | M88: (106594000 - 30% )- (106613000 - 60% )- (300246000 - 10% ) - (PROPORÇÃO)
A89: 802975000 | B89: 12669671 | C89: 299 | D89: 435 | E89: =PRODUCT(C89:D89) -> 130065 | G89: 3.26e-07 | H89: =E89*G89 -> 0.04240119 | J89: 1.8181e-05 | K89: =E89*J89 -> 2.3647118 | L89: PRETO FOSCO
A90: 802979000 | B90: 12004569 | C90: 263 | D90: 427 | E90: =PRODUCT(C90:D90) -> 112301 | G90: 3.26e-07 | H90: =E90*G90 -> 0.036610126 | J90: 1.8181e-05 | K90: =E90*J90 -> 2.0417445 | L90: PRETO FOSCO
A91: 803066000 | B91: 12658580 | C91: 263 | D91: 427 | E91: =PRODUCT(C91:D91) -> 112301 | G91: 3.26e-07 | H91: =E91*G91 -> 0.036610126 | J91: 1.8181e-05 | K91: =E91*J91 -> 2.0417445 | L91: PRETO FOSCO
A92: 803205000 | B92: 10356194 | C92: 821 | D92: 381 | E92: =PRODUCT(C92:D92) -> 312801 | G92: 3.26e-07 | H92: =E92*G92 -> 0.10197313 | J92: 1.8181e-05 | K92: =E92*J92 -> 5.687035 | L92: CINZA TITÂNIO
A93: 803255000 | B93: 12787816 | C93: 686 | D93: 187 | E93: =PRODUCT(C93:D93) -> 128282 | G93: 3.26e-07 | H93: =E93*G93 -> 0.041819932 | J93: 1.8181e-05 | K93: =E93*J93 -> 2.332295 | L93: CINZA TITÂNIO
B94: 12793827 | C94: 755 | D94: 550 | E94: =PRODUCT(C94:D94) -> 415250 | G94: 3.26e-07 | H94: 0.125 | J94: 1.8181e-05 | K94: =E94*J94 -> 7.5496603 | L94: PRETO FOSCO
B95: 10547450 | C95: 667 | D95: 342 | E95: =PRODUCT(C95:D95) -> 228114 | G95: 3.26e-07 | H95: 0.1369 | J95: 1.8181e-05 | K95: 1.64 | L95: RETARDADOR
B96: 12792466 | C96: 569 | D96: 362 | E96: =PRODUCT(C96:D96) -> 205978 | G96: 3.26e-07 | H96: 0.26 | J96: 1.8181e-05 | K96: 3.12 | L96: PRETO FOSCO
B97: 12938713 | C97: 416 | D97: 342 | E97: =PRODUCT(C97:D97) -> 142272 | G97: 3.26e-07 | H97: =E97*G$101 -> 0.046380672 | J97: 1.8181e-05 | K97: =(E97*J97)/2 -> 1.2933236 | L97: PRETO FOSCO | M97: =(H97*57.01)+((195/60)*K97) -> 6.8474639 | O97: =SUM(M97*2) -> 13.694928 | P97: 105479000
B98: 12938722 | C98: 404 | D98: 269 | E98: =PRODUCT(C98:D98) -> 108676 | G98: 3.26e-07 | H98: =E98*G$101 -> 0.035428376 | J98: 1.8181e-05 | K98: =(E98*J98)/2 -> 0.98791918 | L98: PRETO FOSCO | M98: =(H98*57.01)+((195/60)*K98) -> 5.230509 | O98: =SUM(M98*2) -> 10.461018 | P98: 105479000
C100: PARA ORÇAMENTO PINTURA USAR MEDIDA REAL SEM OS 200 PARA CADA LADO | M100: Custo pintura PARA UM LADO DA PEÇA | O100: Custo pintura PARA DOIS LADO DA PEÇA
C101: 182 | D101: 120 | E101: =C101*D101 -> 21840 | F101: =E101/1000000 -> 0.02184 | G101: 3.26e-07 | H101: =E101*G$101 -> 0.00711984 | J101: 1.8181e-05 | K101: =(E101*J101)/2 -> 0.19853652 | L101: PRETO FOSCO | M101: =(H101*79.72)+((K101/60)*175) -> 1.1466585 | O101: =SUM(M101*2) -> 2.293317 | P101: 105479000
C102: 311 | D102: 478.5 | E102: =C102*D102 -> 148813.5 | F102: =E102/1000000 -> 0.1488135 | G102: 3.26e-07 | H102: =E102*G$101 -> 0.048513201 | J102: 1.8181e-05 | K102: =(E102*J102)/2 -> 1.3527891 | L102: PRETO BRILHO | M102: =(H102*33.078)+((K102/60)*175) -> 5.5503546 | O102: =SUM(M102*2) -> 11.100709 | P102: 106580000 / 106586000
C103: 1120 | D103: 140 | E103: =C103*D103 -> 156800 | F103: =E103/1000000 -> 0.1568 | G103: 3.26e-07 | H103: =E103*G$101 -> 0.0511168 | J103: 1.8181e-05 | K103: =(E103*J103)/2 -> 1.4253904 | L103: CINZA TITÂNIO | M103: =(H103*59.95)+((K103/60)*175) -> 7.2218408 | O103: =SUM(M103*2) -> 14.443682 | P103: 105475000
C104: 1000 | D104: 501 | E104: =C104*D104 -> 501000 | F104: =E104/1000000 -> 0.501 | G104: 3.26e-07 | H104: =E104*G$101 -> 0.163326 | J104: 1.8181e-05 | K104: =(E104*J104)/2 -> 4.5543405 | L104: EVO2 | M104: =(H104*48.98)+((K104/60)*175) -> 21.283201 | O104: =SUM(M104*2) -> 42.566401 | P104: 105515000
C105: 500 | D105: 100 | E105: =C105*D105 -> 50000 | F105: =E105/1000000 -> 0.05 | G105: 3.26e-07 | H105: =E105*G$101 -> 0.0163 | J105: 1.8181e-05 | K105: =(E105*J105)/2 -> 0.454525 | L105: RETARDADOR | M105: =(H105*26.46)+((K105/60)*175) -> 1.7569959 | O105: =SUM(M105*2) -> 3.5139918 | P105: 106605000
C106: 95 | D106: 404 | E106: =C106*D106 -> 38380 | F106: =E106/1000000 -> 0.03838 | G106: 3.26e-07 | H106: =E106*G$101 -> 0.01251188 | J106: 1.8181e-05 | K106: =(E106*J106)/2 -> 0.34889339 | L106: ECO2 | M106: =(H106*48.57)+((K106/60)*175) -> 1.6253077 | O106: =SUM(M106*2) -> 3.2506155 | P106: 105861000
C107: 1080 | D107: 1680 | E107: =C107*D107 -> 1814400 | F107: =E107/1000000 -> 1.8144 | G107: 3.26e-07 | H107: =E107*G$101 -> 0.5914944 | J107: 1.8181e-05 | K107: =(E107*J107)/2 -> 16.493803 | L107: ECO3 | M107: =(H107*71.28)+((K107/60)*175) -> 90.268647 | O107: =SUM(M107*2) -> 180.53729 | P107: 105816000
C108: 182 | D108: 120 | E108: =C108*D108 -> 21840 | F108: =E108/1000000 -> 0.02184 | G108: 3.26e-07 | H108: =E108*G$101 -> 0.00711984 | J108: 1.8181e-05 | K108: =(E108*J108)/2 -> 0.19853652 | L108: PRIMER | M108: =(H108*44.56)+((K108/60)*175) -> 0.89632492 | O108: =SUM(M108*2) -> 1.7926498 | P108: 106613000
C109: 518 | D109: 197 | E109: =C109*D109 -> 102046 | F109: =E109/1000000 -> 0.102046 | G109: 3.26e-07 | H109: =E109*G$101 -> 0.033266996 | J109: 1.8181e-05 | K109: =(E109*J109)/2 -> 0.92764916 | L109: CINZA CRISTAL | M109: =(H109*79.72)+((K109/60)*175) -> 5.3576883 | O109: =SUM(M109*2) -> 10.715377 | P109: 106613000
C110: 150 | D110: 195 | E110: =C110*D110 -> 29250 | F110: =E110/1000000 -> 0.02925 | G110: 3.26e-07 | H110: =E110*G$101 -> 0.0095355 | J110: 1.8181e-05 | K110: =(E110*J110)/2 -> 0.26589713 | L110: EVO 1 | M110: =(H110*79.72)+((K110/60)*175) -> 1.5357033 | O110: =SUM(M110*2) -> 3.0714067 | P110: 106186000 | Q110: EM DESENVOLVIMENTO
...

Sheet CENTRO DE CUSTO
A1: VALOR HORA POR CENTRO DE CUSTO
A2: C.C. | B2: DESCRIÇÃO | C2: CUSTO
A3: 312 | B3: MANUTENÇÃO | C3: 80
A4: 322 | B4: MODELARIA | C4: 80
A5: 323 | B5: PINTURA DE PEÇAS - TUNEL | C5: 1400
A6: 325 | B6: FERRAMENTARIA | C6: 80
A7: 338 | B7: PREPARAÇÃO PINTURA CABINE | C7: 188
A8: 339 | B8: ACABAMENTO TERMO FORMAGEM | C8: 105
A9: 343 | B9: TERMO FORMAGEM | C9: 230
A10: 345 | B10: PINTURA PÓ | C10: 170
A11: 348 | B11: CORTE LASER 3D | C11: 340
A12: 358 | B12: P&D | C12: 80
A13: 359 | B13: CORTE E DOBRA | C13: 140
A14: 360 | B14: PRENSAS | C14: 240
... A19: 370 | B19: CORTE LASER 2D | C19: 180

Sheet GRUPO MÁQUINA 2025
A1: Grp Maq | B1: Descrição
A2: 300-001 | B2: ACABAMENTO - ESTILETE
A3: 300-001 | B3: ACABAMENTO - EMBALAR
A4: 300-001 | B4: ACABAMENTO - DIVERSOS
A5: 300-001 | B5: ACABAMENTO - ESTILETE
A6: 301-001 | B6: BANCADA 13 - GUILHOTINA
A7: 301-002 | B7: GUILHOTINA MECANICA NEWTON
A8: 301-003 | B8: GUILHOTINA MECANICA
A9: 301-004 | B9: GUILHOTINA HIDR. GASPARIN
A10: 301-005 | B10: GUILHOTINA NEWTON GHNL
A11: 301-006 | B11: GUILHOTINA NEWTON GMN 2005
A12: 301A | B12: MAQ. SOLDA OXIACETILENO
... A383: 364-002 | B383: ACABAMENTO PU
A384: 367-001 | B384: 3101
A385: 367-002 | B385: TANQUE ESTANQUIEDADE 1 e 2
A386: 367-003 | B386: MAQUINA SOLDA OXIGENIO
A387: 367-004 | B387: BANCADA DE AJUSTE ABERTURA
A388: 367-005 | B388: BANCADA DE AJUSTE PLANICIDADE
A389: 367-007 | B389: GABARITO MONTAGEM ASSOALHO MAN
A390: 367-008 | B390: GABARITO MONTAGEM PAINEL TRAS. MAN
A391: 367-009 | B391: GABARITO MONTAGEM LAT. TRAVES MAN
A392: 367-010 | B392: GABARITO MONTAGEM TETO E FRONTAL MAN
A393: 367-011 | B393: GABARITO MONTAGEM PORTAS MAN
A394: 367-012 | B394: GABARITO MONTAGEM BACIÃO E FECHAM. MAN
A395: 367-013 | B395: MAQ. SOLDA PORCAS QUADRADAS MAN
A396: 367-014 | B396: MAQ. SOLDA PORCAS SEXTAVADA MAN
... A400: TRN2 | B400: TREINAMENTO 2
